{
  "resource": "/{proxy+}",
  "path": "/",
  "httpMethod": "GET",
  "headers": null,
  "multiValueHeaders": null,
  "queryStringParameters": null,
  "multiValueQueryStringParameters": null,
  "pathParameters": null,
  "stageVariables": null,
  "requestContext": {
    "resourceId": "pt7bb8",
    "resourcePath": "/{proxy+}",
    "httpMethod": "GET",
    "extendedRequestId": "NKHUNFDDIE0FbTA=",
    "requestTime": "07/Feb/2022:06:15:03 +0000",
    "path": "/{proxy+}",
    "accountId": "404887138752",
    "protocol": "HTTP/1.1",
    "stage": "test-invoke-stage",
    "domainPrefix": "testPrefix",
    "requestTimeEpoch": 1644214503535,
    "requestId": "e9cd628f-8d7c-4a76-99c2-355c474c0a27",
    "identity": {
      "cognitoIdentityPoolId": null,
      "cognitoIdentityId": null,
      "apiKey": "test-invoke-api-key",
      "principalOrgId": null,
      "cognitoAuthenticationType": null,
      "userArn": "arn:aws:iam::404887138752:root",
      "apiKeyId": "test-invoke-api-key-id",
      "userAgent": "aws-internal/3 aws-sdk-java/1.12.138 Linux/5.4.156-94.273.amzn2int.x86_64 OpenJDK_64-Bit_Server_VM/25.312-b07 java/1.8.0_312 vendor/Oracle_Corporation cfg/retry-mode/standard",
      "accountId": "404887138752",
      "caller": "404887138752",
      "sourceIp": "test-invoke-source-ip",
      "accessKey": "ASIAV4RJHOHAGAL22IPV",
      "cognitoAuthenticationProvider": null,
      "user": "404887138752"
    },
    "domainName": "testPrefix.testDomainName",
    "apiId": "8ehqqk75y7"
  },
  "body": null,
  "isBase64Encoded": false
}
